LGPmodule/__init__.py
LGPmodule/main.py
LGPmodule-1.1.0.dist-info/METADATA
LGPmodule-1.1.0.dist-info/WHEEL
LGPmodule-1.1.0.dist-info/top_level.txt
LGPmodule-1.1.0.dist-info/RECORD
