Metadata-Version: 2.2
Name: LGPmodule
Version: 1.1.0
Summary: Just a small package used in little guy's projects.
Author: Grumm
Dynamic: author
Dynamic: description
Dynamic: description-content-type
Dynamic: summary
